dailypublisherrevenue/__init__.py
dailypublisherrevenue/dailyrevenue.py
lasttest-1.0.dist-info/METADATA
lasttest-1.0.dist-info/WHEEL
lasttest-1.0.dist-info/top_level.txt
lasttest-1.0.dist-info/RECORD
